README
setup.py
timebook/__init__.py
timebook/cmdline.py
timebook/cmdutil.py
timebook/commands.py
timebook/config.py
timebook/db.py
timebook/dbutil.py
timebook.egg-info/PKG-INFO
timebook.egg-info/SOURCES.txt
timebook.egg-info/dependency_links.txt
timebook.egg-info/entry_points.txt
timebook.egg-info/top_level.txt