Metadata-Version: 1.0
Name: timebook
Version: 1.2.0
Summary: track what you spend time on
Home-page: http://bitbucket.org/trevor/timebook/
Author: Trevor Caira
Author-email: trevor@caira.com
License: UNKNOWN
Platform: UNKNOWN
Classifier: Development Status :: 4 - Beta
Classifier: Environment :: Console
Classifier: Intended Audience :: Developers
Classifier: License :: OSI Approved :: MIT License
Classifier: Operating System :: OS Independent
Classifier: Programming Language :: Python
Classifier: Topic :: Utilities
